proxytg/__init__.py
proxytg/telegram.py
tests/__init__.py
tests/test_telegram.py
proxytg-0.2.0.dist-info/METADATA
proxytg-0.2.0.dist-info/WHEEL
proxytg-0.2.0.dist-info/top_level.txt
proxytg-0.2.0.dist-info/RECORD
